CopperUI/__init__.py
CopperUI/__main__.py
CopperUI/colors.py
CopperUI/copperhead.py
CopperUI/errors.py
CopperUI/logs.py
CopperUI-3.5.2.dist-info/LICENSE
CopperUI-3.5.2.dist-info/METADATA
CopperUI-3.5.2.dist-info/WHEEL
CopperUI-3.5.2.dist-info/top_level.txt
CopperUI-3.5.2.dist-info/RECORD
