Metadata-Version: 2.1
Name: CopperUI
Version: 3.5.2
Summary: a TUI helper package
Home-page: https://github.com/Copperhead-software/CopperUI/
Author: Morgan Metz
Author-email: mlmi4@k12albemarle.org
Project-URL: Bug Tracker, https://github.com/Copperhead-software/CopperUI/issues
Classifier: Programming Language :: Python :: 3
Classifier: License :: OSI Approved :: MIT License
Classifier: Operating System :: OS Independent
Requires-Python: >=3.0
License-File: LICENSE
